dbrequest/__init__.py
dbrequest/exceptions.py
dbrequest/interfaces.py
dbrequest/py.typed
dbrequest/config/config.py
dbrequest/core/__init__.py
dbrequest/core/fields.py
dbrequest/core/requests.py
dbrequest/core/serializer.py
dbrequest/core/type_converters.py
dbrequest/core/universal_requests.py
dbrequest/executors/__init__.py
dbrequest/executors/sqlite_executor.py
dbrequest/executors/universal_executor.py
dbrequest/sql/__init__.py
dbrequest/sql/properties.py
dbrequest/sql/requests.py
dbrequest-0.2.1.dist-info/METADATA
dbrequest-0.2.1.dist-info/WHEEL
dbrequest-0.2.1.dist-info/licenses/LICENSE
dbrequest-0.2.1.dist-info/RECORD
