Metadata-Version: 2.3
Name: dbrequest
Version: 0.2.1
Summary: Simple ORM library for easy database handling.
Project-URL: Github, https://github.com/korandr/dbrequest
Project-URL: Documentation, https://github.com/korandr/dbrequest/wiki
Author-email: korandr <andrey.korovyansky@gmail.com>
License-File: LICENSE
Classifier: Development Status :: 4 - Beta
Classifier: License :: OSI Approved :: MIT License
Classifier: Operating System :: OS Independent
Classifier: Programming Language :: Python :: 3
Classifier: Topic :: Database
Classifier: Topic :: Documentation
Requires-Python: >=3.10
